afsql/db_redis.py
afsql/db_sqlit3.py
afsql/mysql.py
afsql/postgresql.py
afsql/py2neo4j.py
afsql/pyneo4j_ban.py
afsql-0.2.3.3.dist-info/WHEEL
afsql-0.2.3.3.dist-info/METADATA
afsql-0.2.3.3.dist-info/RECORD
