Metadata-Version: 2.1
Name: afsql
Version: 0.2.3.3
Summary: 
License: MIT
Author: Asdil
Requires-Python: >=3.6,<4.0
Classifier: License :: OSI Approved :: MIT License
Classifier: Programming Language :: Python :: 3
Classifier: Programming Language :: Python :: 3.10
Classifier: Programming Language :: Python :: 3.6
Classifier: Programming Language :: Python :: 3.7
Classifier: Programming Language :: Python :: 3.8
Classifier: Programming Language :: Python :: 3.9
Requires-Dist: DBUtils (>=2.0,<3.0)
Requires-Dist: PyMySQL (>=1.0.2,<2.0.0)
Requires-Dist: psycopg2-binary (>=2.8.6,<3.0.0)
Requires-Dist: py2neo (>=2021.2.3,<2022.0.0)
